pyrendering/__init__.py
pyrendering/camera.py
pyrendering/color.py
pyrendering/context.py
pyrendering/engine.py
pyrendering/font.py
pyrendering/graphics.py
pyrendering/py.typed
pyrendering/shapes.py
pyrendering/vectors.py
pyrendering-0.1.6.dist-info/WHEEL
pyrendering-0.1.6.dist-info/METADATA
pyrendering-0.1.6.dist-info/RECORD
