Metadata-Version: 2.3
Name: pyrendering
Version: 0.1.6
Summary: Python game building/rendering framework
Author: ShyMike
Author-email: ShyMike <122023566+ImShyMike@users.noreply.github.com>
Requires-Dist: glfw>=2.10.0
Requires-Dist: moderngl>=5.12.0
Requires-Dist: numpy==2.3.3
Requires-Dist: pillow>=11.3.0
Requires-Python: >=3.11
